hologenerator/__init__.py
hologenerator/__main__.py
hologenerator/core/changes_ini.py
hologenerator/core/differ.py
hologenerator/core/generator.py
hologenerator/gui/__init__.py
hologenerator/gui/main.py
hologenerator/tests/__init__.py
hologenerator/tests/test_cli.py
hologenerator/tests/test_core.py
hologenerator/tests/test_gui.py
hologenerator-1.0.1.dist-info/METADATA
hologenerator-1.0.1.dist-info/WHEEL
hologenerator-1.0.1.dist-info/entry_points.txt
hologenerator-1.0.1.dist-info/top_level.txt
hologenerator-1.0.1.dist-info/RECORD
