Metadata-Version: 2.4
Name: hologenerator
Version: 1.0.1
Summary: KOTOR Configuration Generator for HoloPatcher - GUI and CLI tool
Author-email: th3w1zard1 <halomastar@gmail.com>
Maintainer-email: th3w1zard1 <halomastar@gmail.com>
License: MIT
Project-URL: Homepage, https://github.com/OldRepublicDevs/PyKotor
Project-URL: Documentation, https://github.com/OldRepublicDevs/PyKotor/wiki
Project-URL: Repository, https://github.com/OldRepublicDevs/PyKotor.git
Project-URL: Issues, https://github.com/OldRepublicDevs/PyKotor/issues
Project-URL: Changelog, https://github.com/OldRepublicDevs/PyKotor/releases
Keywords: kotor,kotor1,kotor2,tsl,config,generator,holopatcher,tslpatcher,modding,pykotor
Classifier: Development Status :: 4 - Beta
Classifier: Intended Audience :: Developers
Classifier: License :: OSI Approved :: MIT License
Classifier: Operating System :: OS Independent
Classifier: Programming Language :: Python :: 3
Classifier: Programming Language :: Python :: 3.8
Classifier: Programming Language :: Python :: 3.9
Classifier: Programming Language :: Python :: 3.10
Classifier: Programming Language :: Python :: 3.11
Classifier: Programming Language :: Python :: 3.12
Classifier: Topic :: Games/Entertainment
Classifier: Topic :: Software Development :: Code Generators
Classifier: Topic :: Utilities
Classifier: Environment :: Console
Classifier: Environment :: Web Environment
Requires-Python: >=3.8
Requires-Dist: pykotor>=2.0.2
Provides-Extra: gui
Provides-Extra: web
Requires-Dist: flask; extra == "web"
Requires-Dist: flask-cors; extra == "web"
Provides-Extra: dev
Requires-Dist: pytest>=7.0.0; extra == "dev"
Requires-Dist: ruff>=0.1.0; extra == "dev"
